instrument_server/__init__.py
instrument_server/helpers.py
instrument_server/instrument_server.py
instrument_server/yaml.py
instrument_server/application/__init__.py
instrument_server/application/application.py
instrument_server/application/helpers.py
instrument_server/bin/__init__.py
instrument_server/bin/instrument_server.py
instrument_server/client/__init__.py
instrument_server/client/client.py
instrument_server/client/command_parser.py
instrument_server/client/helpers.py
instrument_server/command_line/__init__.py
instrument_server/command_line/helpers.py
instrument_server/command_line/main.py
instrument_server/commands/__init__.py
instrument_server/commands/basic_command.py
instrument_server/commands/command_base.py
instrument_server/commands/command_parser.py
instrument_server/commands/errors_command.py
instrument_server/commands/quit_command.py
instrument_server/commands/mixins/__init__.py
instrument_server/commands/mixins/raise_error.py
instrument_server/devices/__init__.py
instrument_server/devices/device_factory_base.py
instrument_server/devices/socket_factory.py
instrument_server/devices/visa_factory.py
instrument_server/devices/mixins/__init__.py
instrument_server/devices/mixins/raise_error.py
instrument_server/errors/__init__.py
instrument_server/errors/command_error.py
instrument_server/errors/command_not_found_error.py
instrument_server/errors/device_error.py
instrument_server/errors/open_device_error.py
instrument_server/errors/plugin_error.py
instrument_server/plugin_manager/__init__.py
instrument_server/plugin_manager/helpers.py
instrument_server/plugin_manager/plugin_manager.py
instrument_server/plugin_manager/command_plugin_manager/__init__.py
instrument_server/plugin_manager/command_plugin_manager/command_plugin_manager.py
instrument_server/plugin_manager/command_plugin_manager/helpers.py
instrument_server/plugin_manager/device_factory_plugin_manager/__init__.py
instrument_server-2.1.2.dist-info/METADATA
instrument_server-2.1.2.dist-info/WHEEL
instrument_server-2.1.2.dist-info/entry_points.txt
instrument_server-2.1.2.dist-info/top_level.txt
instrument_server-2.1.2.dist-info/RECORD
