Metadata-Version: 2.1
Name: instrument-server
Version: 2.1.2
Summary: A tool for creating Test and Measurement microservices
Home-page: https://github.com/Terrabits/instrument-server
Author: Nick Lalic
Author-email: nick.lalic@gmail.com
License: R&S Terms and Conditions for Royalty-Free Products
Keywords: RF instrument SCPI
Platform: UNKNOWN
Classifier: Development Status :: 4 - Beta
Classifier: Environment :: Console
Classifier: Operating System :: MacOS :: MacOS X
Classifier: Operating System :: Microsoft :: Windows
Classifier: Operating System :: POSIX
Classifier: Operating System :: Unix
Classifier: Intended Audience :: Developers
Classifier: Topic :: Scientific/Engineering
Classifier: License :: Other/Proprietary License
Classifier: Programming Language :: Python :: 3.7
Classifier: Programming Language :: Python :: 3.8
Classifier: Programming Language :: Python :: 3.9
Classifier: Programming Language :: Python :: 3.10
Requires-Dist: ruamel.yaml (>=0.15.85<1.0)
Requires-Dist: pyvisa (>=1.9.1<2.0)
Provides-Extra: dev
Requires-Dist: ddt (>=1.2.0<2.0) ; extra == 'dev'
Requires-Dist: twine (>=3.8.0) ; extra == 'dev'
Requires-Dist: wheel (>=0.37.1) ; extra == 'dev'
Provides-Extra: dist
Requires-Dist: twine (>=3.8.0) ; extra == 'dist'
Requires-Dist: wheel (>=0.37.1) ; extra == 'dist'
Provides-Extra: test
Requires-Dist: ddt (>=1.2.0<2.0) ; extra == 'test'
